Metadata-Version: 1.1
Name: m2m-certificates
Version: 0.1.1
Summary: Python module for generating and parsing M2M format certificates
Home-page: https://github.com/LoyVanBeek/m2m_certificates
Author: Loy van Beek
Author-email: l.vanbeek@ultimaker.com
License: AGPL
Download-URL: https://github.com/LoyVanBeek/m2m_certificates/tarball/0.1
Keywords: nfc ndef m2m
Platform: UNKNOWN
Classifier: Development Status :: 3 - Alpha
Classifier: License :: OSI Approved :: GNU Affero General Public License v3
Classifier: Programming Language :: Python :: 3
Classifier: Programming Language :: Python :: 3.5
Classifier: Intended Audience :: Developers
Classifier: Topic :: Software Development :: Libraries :: Python Modules
Classifier: Topic :: Security :: Cryptography
